{
  "project_info": {
    "project_number": "276947768295",
    "project_id": "ifood-f6a84",
    "storage_bucket": "ifood-f6a84.firebasestorage.app"
  },
  "client": [
    {
      "client_info": {
        "mobilesdk_app_id": "1:276947768295:android:2c62ed78512256f937a342",
        "android_client_info": {
          "package_name": "com.example.ifoodclone"
        }
      },
      "oauth_client": [],
      "api_key": [
        {
          "current_key": "AIzaSyAunGnbfYCQ-PQCNqAOjxSoCNUDU03xTss"
        }
      ],
      "services": {
        "appinvite_service": {
          "other_platform_oauth_client": []
        }
      }
    }
  ],
  "configuration_version": "1"
}